turtlefy/__init__.py
turtlefy/__main__.py
turtlefy/client.py
turtlefy/filters.py
turtlefy/hooks.py
turtlefy/resources.py
turtlefy-0.8.12.dist-info/LICENSE
turtlefy-0.8.12.dist-info/METADATA
turtlefy-0.8.12.dist-info/WHEEL
turtlefy-0.8.12.dist-info/top_level.txt
turtlefy-0.8.12.dist-info/RECORD
