Metadata-Version: 2.1
Name: turtlefy
Version: 0.8.12
Summary: A collection of Shopify utilities to make life easier.
Home-page: https://github.com/nprutan/turtlefy
Author: Nate Rutan
Author-email: nathan@composedcloud.com
License: MIT
Platform: UNKNOWN
Classifier: License :: OSI Approved :: MIT License
Classifier: Programming Language :: Python
Classifier: Programming Language :: Python :: 3.7
Classifier: Programming Language :: Python :: 3.8
Classifier: Programming Language :: Python :: Implementation :: CPython
Classifier: Programming Language :: Python :: Implementation :: PyPy
Requires-Python: >=3.7.0
Requires-Dist: requests
